eal_dist/__init__.py
eal_dist-25.7.10.dist-info/LICENSE
eal_dist-25.7.10.dist-info/METADATA
eal_dist-25.7.10.dist-info/WHEEL
eal_dist-25.7.10.dist-info/top_level.txt
eal_dist-25.7.10.dist-info/RECORD
