Metadata-Version: 2.1
Name: eal_dist
Version: 25.7.10
Summary: Object tracking software for EAL
Home-page: https://easyaimlock.com
Author: EasyAimLock
Author-email: support@easyaimlock.com
Project-URL: Bug Tracker, https://easyaimlock.com
Classifier: Programming Language :: Python :: 3
Classifier: License :: OSI Approved :: MIT License
Classifier: Operating System :: OS Independent
Requires-Python: >=3.12
License-File: LICENSE
Requires-Dist: mediapipe
